adtools/ADTools.py
adtools/ADToolsLog.py
adtools/LdapCommands.py
adtools/__init__.py
adtools/exceptions.py
adtools/sid.py
adtools/utils.py
adtools/objects/ADObject.py
adtools/objects/Computer.py
adtools/objects/Group.py
adtools/objects/OrganizationalUnit.py
adtools/objects/User.py
adtools/objects/__init__.py
tests/__init__.py
tests/test_search.py
adtools-1.2.1.dist-info/LICENSE
adtools-1.2.1.dist-info/METADATA
adtools-1.2.1.dist-info/WHEEL
adtools-1.2.1.dist-info/top_level.txt
adtools-1.2.1.dist-info/RECORD
